graphs_snakkattack/__init__.py
graphs_snakkattack/heapq.py
graphs_snakkattack/sp.py
graphs_snakkattack-0.1.0.dist-info/METADATA
graphs_snakkattack-0.1.0.dist-info/WHEEL
graphs_snakkattack-0.1.0.dist-info/top_level.txt
graphs_snakkattack-0.1.0.dist-info/RECORD
