Metadata-Version: 2.4
Name: graphs_SnakkAttack
Version: 0.1.0
Summary: Graph algorithms (Dijkstra's shortest paths, etc.)
Author: Gage Gunn
License: MIT
Project-URL: Homepage, https://github.com/SnakkAttack/graphs_SnakkAttack
Project-URL: Issues, https://github.com/SnakkAttack/graphs_SnakkAttack/issues
Keywords: graphs,dijkstra,shortest path,algorithms
Requires-Python: >=3.9
